LICENSE
MANIFEST.in
README.md
setup.cfg
setup.py
examples/blog/blogs.yml
examples/blog/categries.yml
examples/blog/comments.yml
examples/blog/tags.yml
examples/blog/users.yml
xdocs/__init__.py
xdocs/__main__.py
xdocs/server.py
xdocs.egg-info/PKG-INFO
xdocs.egg-info/SOURCES.txt
xdocs.egg-info/dependency_links.txt
xdocs.egg-info/entry_points.txt
xdocs.egg-info/not-zip-safe
xdocs.egg-info/requires.txt
xdocs.egg-info/top_level.txt
xdocs/client/index.html
xdocs/client/static/index.css
xdocs/client/static/vue.min.js
xdocs/client/static/xdocs.js
xdocs/client/static/yaml.js